{
  "ControllerMap": "CompControllerMap",
  "SparkMaxPositionConfigs": [
    {
      "AbsolutePositionConversionFactor": 1,
      "AbsoluteVelocityConversionFactor": 1,
      "AbsoluteZeroOffset": 0.515,
      "CurrentLimit": 45,
      "DefaultRunMode": "RELATIVE",
      "ID": 31,
      "IdleMode": "Brake",
      "InvertedAbsolute": true,
      "InvertedRelative": false,
      "MaxSpeed": 0.5,
      "MinSpeed": -0.5,
      "Name": "ExtenderMotor",
      "Follow": "NONE",
      "PositionPID": {
        "D": 0,
        "FF": 0,
        "I": 0,
        "P": 0.3
      },
      "PositionPIDWrappingEnabled": false,
      "RelativePositionConversionFactor": 0.74862,
      "RelativeVelocityConversionFactor": 1,
      "TurningEncoderPositionPIDMaxInput": 0,
      "TurningEncoderPositionPIDMinInput": 0,
      "VelocityPID": {
        "D": 0,
        "FF": 0,
        "I": 0,
        "P": 0
      },
      "ForwardSoftLimitEnabled": true,
      "ReverseSoftLimitEnabled": true,
      "ForwardSoftLimit": 18.5,
      "ReverseSoftLimit": 0.5,
      "Positions":
      {
          "ExtenderHomePosition": 0.1,
          "ExtenderHighCubePosition": 16.25,
          "ExtenderHighConePosition": 18.25,
          "ExtenderMidCubePosition": 0.2,
          "ExtenderMidConePosition": 0.2,
          "ExtenderLowCubePosition": 12,
          "ExtenderLowConePosition": 11,
          "ExtenderUpRightConePosition": 12,
          "ExtenderSideConePosition": 13,
          "ExtenderCubePosition": 12,
          "ExtenderSingleSubPosition": 0,
          "ExtenderDoubleSubPosition": 0
      }
    },
    {
      "AbsolutePositionConversionFactor": 360,
      "AbsoluteVelocityConversionFactor": 1,
      "AbsoluteZeroOffset": 80,
      "CurrentLimit": 45,
      "DefaultRunMode": "ABSOLUTE",
      "ID": 21,
      "IdleMode": "Brake",
      "InvertedAbsolute": false,
      "InvertedRelative": true,
      "MaxSpeed": 0.5,
      "MinSpeed": -0.5,
      "Name": "ElbowMotor",
      "Follow": "NONE",
      "PositionPID": {
        "D": 0.25,
        "FF": 0,
        "I": 0,
        "P": 0.0075
      },
      "PositionPIDWrappingEnabled": false,
      "RelativePositionConversionFactor": 7.776,
      "RelativeVelocityConversionFactor": 1,
      "TurningEncoderPositionPIDMaxInput": 0,
      "TurningEncoderPositionPIDMinInput": 0,
      "VelocityPID": {
        "D": 0,
        "FF": 0,
        "I": 0,
        "P": 1
      },
      "ForwardSoftLimitEnabled": true,
      "ReverseSoftLimitEnabled": true,
      "ForwardSoftLimit": 299, 
      "ReverseSoftLimit": 15, 
      "Positions":
      {
        "ElbowHomePosition": 12,
        "ElbowHighCubePosition": 222,
        "ElbowHighConePosition": 212.1,
        "ElbowMidCubePosition": 246.5,
        "ElbowMidConePosition": 234.2,
        "ElbowLowCubePosition": 32.6,
        "ElbowLowConePosition": 37.6,
        "ElbowUpRightConePosition": 26.8,
        "ElbowSideConePosition": 23.4,
        "ElbowCubePosition": 30.6,
        "ElbowSingleSubPosition": 0,
        "ElbowDoubleSubPosition": 0
      }
    },
    {
      "AbsolutePositionConversionFactor": 1,
      "AbsoluteVelocityConversionFactor": 1,
      "AbsoluteZeroOffset": 0,
      "CurrentLimit": 45,
      "DefaultRunMode": "ABSOLUTE",
      "ID": 20,
      "IdleMode": "Brake",
      "InvertedAbsolute": false,
      "InvertedRelative": true,
      "MaxSpeed": 0.5,
      "MinSpeed": -0.5,
      "Name": "ElbowMotorFollow",
      "Follow": "ElbowMotor",
      "PositionPID": {
        "D": 0,
        "FF": 0,
        "I": 0,
        "P": 0
      },
      "PositionPIDWrappingEnabled": false,
      "RelativePositionConversionFactor": 1,
      "RelativeVelocityConversionFactor": 1,
      "TurningEncoderPositionPIDMaxInput": 0,
      "TurningEncoderPositionPIDMinInput": 0,
      "VelocityPID": {
        "D": 0,
        "FF": 0,
        "I": 0,
        "P": 0
      },
      "ForwardSoftLimitEnabled": false,
      "ReverseSoftLimitEnabled": false,
      "ForwardSoftLimit": 0,
      "ReverseSoftLimit": 0,
      "Positions":
      {
        "ElbowHomePosition": 10,
        "ElbowHighCubePosition": 0,
        "ElbowHighConePosition": 0,
        "ElbowMidCubePosition": 0,
        "ElbowMidConePosition": 0,
        "ElbowLowCubePosition": 0,
        "ElbowLowConePosition": 0,
        "ElbowUpRightConePosition": 0,
        "ElbowSideConePosition": 0,
        "ElbowCubePosition": 0,
        "ElbowSingleSubPosition": 0,
        "ElbowDoubleSubPosition": 0
      }
    },
    {

      "AbsolutePositionConversionFactor": 360,
      "AbsoluteVelocityConversionFactor": 1,
      "AbsoluteZeroOffset": 51,
      "CurrentLimit": 20,
      "DefaultRunMode": "ABSOLUTE",
      "ID": 32,
      "IdleMode": "Brake",
      "InvertedAbsolute": false,
      "InvertedRelative": false,
      "MaxSpeed": 0.5,
      "MinSpeed": -0.5,
      "Name": "WristMotor",
      "Follow": "NONE",
      "PositionPID": {
        "D": 0,
        "FF": 0,
        "I": 0,
        "P": 0.04
      },
      "PositionPIDWrappingEnabled": false,
      "RelativePositionConversionFactor": 2.26,
      "RelativeVelocityConversionFactor": 1,
      "TurningEncoderPositionPIDMaxInput": 0,
      "TurningEncoderPositionPIDMinInput": 0,
      "VelocityPID": {
        "D": 0,
        "FF": 0,
        "I": 0,
        "P": 0
      },
      "ForwardSoftLimitEnabled": true,
      "ReverseSoftLimitEnabled": true,
      "ForwardSoftLimit": 350,
      "ReverseSoftLimit": 10,
      "Positions":
      {
        "WristHomePosition": 45,
        "WristHighCubePosition": 45,
        "WristHighConePosition": 315,
        "WristMidCubePosition": 45,
        "WristMidConePosition": 315,
        "WristLowCubePosition": 45,
        "WristLowConePosition": 135,
        "WristUpRightConePosition": 135,
        "WristSideConePosition": 45,
        "WristCubePosition": 225,
        "WristSingleSubPosition": 0,
        "WristDoubleSubPosition": 0
      }
    },
    {
      "AbsolutePositionConversionFactor": 6.2831853072000001,
      "AbsoluteVelocityConversionFactor": 0.104719755,
      "AbsoluteZeroOffset": 0,
      "CurrentLimit": 10,
      "DefaultRunMode": "ABSOLUTE",
      "ID": 2,
      "IdleMode": "Brake",
      "InvertedAbsolute": true,
      "InvertedRelative": false,
      "MaxSpeed": 1,
      "MinSpeed": -1,
      "Name": "AzimuthMotor1",
      "Follow": "NONE",
      "PositionPID": {
        "D": 0,
        "FF": 0,
        "I": 0,
        "P": 1
      },
      "PositionPIDWrappingEnabled": true,
      "RelativePositionConversionFactor": 1,
      "RelativeVelocityConversionFactor": 1,
      "TurningEncoderPositionPIDMaxInput": 6.2831853072000001,
      "TurningEncoderPositionPIDMinInput": 0,
      "VelocityPID": {
        "D": 0,
        "FF": 0,
        "I": 0,
        "P": 0
      },
      "ForwardSoftLimitEnabled": false,
      "ReverseSoftLimitEnabled": false,
      "ForwardSoftLimit": 0,
      "ReverseSoftLimit": 0,
      "Positions":
      {
        
      }
    },
    {
      "AbsolutePositionConversionFactor": 6.2831853072000001,
      "AbsoluteVelocityConversionFactor": 0.104719755,
      "AbsoluteZeroOffset": 0,
      "CurrentLimit": 10,
      "DefaultRunMode": "ABSOLUTE",
      "ID": 4,
      "IdleMode": "Brake",
      "InvertedAbsolute": true,
      "InvertedRelative": false,
      "MaxSpeed": 1,
      "MinSpeed": -1,
      "Name": "AzimuthMotor2",
      "Follow": "NONE",
      "PositionPID": {
        "D": 0,
        "FF": 0,
        "I": 0,
        "P": 1
      },
      "PositionPIDWrappingEnabled": true,
      "RelativePositionConversionFactor": 1,
      "RelativeVelocityConversionFactor": 1,
      "TurningEncoderPositionPIDMaxInput": 6.2831853072000001,
      "TurningEncoderPositionPIDMinInput": 0,
      "VelocityPID": {
        "D": 0,
        "FF": 0,
        "I": 0,
        "P": 0
      },
      "ForwardSoftLimitEnabled": false,
      "ReverseSoftLimitEnabled": false,
      "ForwardSoftLimit": 0,
      "ReverseSoftLimit": 0,
      "Positions":
      {
        
      }
    },
    {
      "AbsolutePositionConversionFactor": 6.2831853072000001,
      "AbsoluteVelocityConversionFactor": 0.104719755,
      "AbsoluteZeroOffset": 0,
      "CurrentLimit": 10,
      "DefaultRunMode": "ABSOLUTE",
      "ID": 6,
      "IdleMode": "Brake",
      "InvertedAbsolute": true,
      "InvertedRelative": false,
      "MaxSpeed": 1,
      "MinSpeed": -1,
      "Name": "AzimuthMotor3",
      "Follow": "NONE",
      "PositionPID": {
        "D": 0,
        "FF": 0,
        "I": 0,
        "P": 1
      },
      "PositionPIDWrappingEnabled": true,
      "RelativePositionConversionFactor": 1,
      "RelativeVelocityConversionFactor": 1,
      "TurningEncoderPositionPIDMaxInput": 6.2831853072000001,
      "TurningEncoderPositionPIDMinInput": 0,
      "VelocityPID": {
        "D": 0,
        "FF": 0,
        "I": 0,
        "P": 0
      },
      "ForwardSoftLimitEnabled": false,
      "ReverseSoftLimitEnabled": false,
      "ForwardSoftLimit": 0,
      "ReverseSoftLimit": 0,
      "Positions":
      {
        
      }
    },
    {
      "AbsolutePositionConversionFactor": 6.2831853072000001,
      "AbsoluteVelocityConversionFactor": 0.104719755,
      "AbsoluteZeroOffset": 0,
      "CurrentLimit": 10,
      "DefaultRunMode": "ABSOLUTE",
      "ID": 8,
      "IdleMode": "Brake",
      "InvertedAbsolute": true,
      "InvertedRelative": false,
      "MaxSpeed": 1,
      "MinSpeed": -1,
      "Name": "AzimuthMotor4",
      "Follow": "NONE",
      "PositionPID": {
        "D": 0,
        "FF": 0,
        "I": 0,
        "P": 1
      },
      "PositionPIDWrappingEnabled": true,
      "RelativePositionConversionFactor": 1,
      "RelativeVelocityConversionFactor": 1,
      "TurningEncoderPositionPIDMaxInput": 6.2831853072000001,
      "TurningEncoderPositionPIDMinInput": 0,
      "VelocityPID": {
        "D": 0,
        "FF": 0,
        "I": 0,
        "P": 0
      },
      "ForwardSoftLimitEnabled": false,
      "ReverseSoftLimitEnabled": false,
      "ForwardSoftLimit": 0,
      "ReverseSoftLimit": 0,
      "Positions":
      {
        
      }
    }
  ],
  "SparkMaxPercentConfigs": [
    {
      "Name": "EndEffectorMotor",
      "ID": 41,
      "InvertedRelative": false,
      "CurrentLimit": 20,
      "IdleMode": "Brake",
      "Follow": "NONE",
      "Percents":
      {
        "EndEffectorConeInputPercent": 0.75,
        "EndEffectorCubeInputPercent": -0.2,
        "EndEffectorConeHoldPercent": 0.05,
        "EndEffectorCubeHoldPercent": -0.05
      }
    }
  ],
  "SparkMaxPWMConfigs": [],
  "SwerveConfigs": [
    {
      "BackLeftModule": "Module3",
      "BackRightModule": "Module4",
      "DirectionSlewRate": 1.2,
      "FrontLeftModule": "Module1",
      "FrontRightModule": "Module2",
      "MagnitudeSlewRate": 5,
      "MaxSpeed": 5,
      "MaxTurnSpeed": 6.2829999999999999,
      "Name": "Swerve",
      "RotationalSlewRate": 2,
      "TrackWidth": 0.67310000000000003,
      "WheelBase": 0.67310000000000003
    }
  ],
  "SwerveModuleConfigs": [
    {
      "AngularOffset": -1.57079633,
      "Azimuth": "AzimuthMotor1",
      "Drive": "DriveMotor1",
      "Name": "Module1"
    },
    {
      "AngularOffset": 0,
      "Azimuth": "AzimuthMotor2",
      "Drive": "DriveMotor2",
      "Name": "Module2"
    },
    {
      "AngularOffset": 3.1415926,
      "Azimuth": "AzimuthMotor3",
      "Drive": "DriveMotor3",
      "Name": "Module3"
    },
    {
      "AngularOffset": 1.57079633,
      "Azimuth": "AzimuthMotor4",
      "Drive": "DriveMotor4",
      "Name": "Module4"
    }
  ],
  "SparkMaxVelocityConfigs": [
    {
      "CurrentLimit": 60,
      "ID": 1,
      "IdleMode": "Brake",
      "InvertedRelative": false,
      "Name": "DriveMotor1",
      "RelativePositionConversionFactor": 0.0727910427491711,
      "RelativeVelocityConversionFactor": 0.00084632602091900004,
      "Follow": "NONE",
      "VelocityPID": {
        "D": 0,
        "FF": 0.20817085187419279,
        "I": 0,
        "P": 0.040000000000000001
      },
      "Velocities":
      {

      }
    },
    {
      "CurrentLimit": 60,
      "ID": 3,
      "IdleMode": "Brake",
      "InvertedRelative": false,
      "Name": "DriveMotor2",
      "RelativePositionConversionFactor": 0.0727910427491711,
      "RelativeVelocityConversionFactor": 0.00084632602091900004,
      "Follow": "NONE",
      "VelocityPID": {
        "D": 0,
        "FF": 0.20817085187419279,
        "I": 0,
        "P": 0.040000000000000001
      },
      "Velocities":
      {
        
      }
    },
    {
      "CurrentLimit": 60,
      "ID": 5,
      "IdleMode": "Brake",
      "InvertedRelative": false,
      "Name": "DriveMotor3",
      "RelativePositionConversionFactor": 0.0727910427491711,
      "RelativeVelocityConversionFactor": 0.00084632602091900004,
      "Follow": "NONE",
      "VelocityPID": {
        "D": 0,
        "FF": 0.20817085187419279,
        "I": 0,
        "P": 0.040000000000000001
      },
      "Velocities":
      {
        
      }
    },
    {
      "CurrentLimit": 60,
      "ID": 7,
      "IdleMode": "Brake",
      "InvertedRelative": false,
      "Name": "DriveMotor4",
      "RelativePositionConversionFactor": 0.0727910427491711,
      "RelativeVelocityConversionFactor": 0.00084632602091900004,
      "Follow": "NONE",
      "VelocityPID": {
        "D": 0,
        "FF": 0.20817085187419279,
        "I": 0,
        "P": 0.040000000000000001
      },
      "Velocities":
      {
        
      }
    }
  ]
}
